jupyter_kernel_test/__init__.py
jupyter_kernel_test/msgspec_v5.py
jupyter_kernel_test-0.7.0.dist-info/METADATA
jupyter_kernel_test-0.7.0.dist-info/WHEEL
jupyter_kernel_test-0.7.0.dist-info/licenses/LICENSE
jupyter_kernel_test-0.7.0.dist-info/RECORD
