Metadata-Version: 2.1
Name: jupyter_kernel_test
Version: 0.7.0
Project-URL: Homepage, https://github.com/jupyter/jupyter_kernel_test
Author-email: Jupyter Development Team <jupyter@googlegroups.com>
License: Copyright (c) 2015-2021 Project Jupyter Contributors
License-File: LICENSE
Classifier: Intended Audience :: Developers
Classifier: License :: OSI Approved :: BSD License
Classifier: Programming Language :: Python :: 3
Classifier: Topic :: Software Development :: Testing
Requires-Python: >=3.8
Requires-Dist: jsonschema
Requires-Dist: jupyter-client>=6.1.13
Provides-Extra: test
Requires-Dist: ipykernel; extra == 'test'
Requires-Dist: pre-commit; extra == 'test'
